lock/__init__.py
lock/cli.py
lock/lock.py
lock/parser.py
lock_requirements-0.1.1.dist-info/METADATA
lock_requirements-0.1.1.dist-info/WHEEL
lock_requirements-0.1.1.dist-info/entry_points.txt
lock_requirements-0.1.1.dist-info/top_level.txt
lock_requirements-0.1.1.dist-info/RECORD
