Metadata-Version: 2.1
Name: lock-requirements
Version: 0.1.1
Summary: A CLI tool to update your requirements.txt file package versions to be locked/fixed to the latest versions available on PyPI.
Home-page: UNKNOWN
Author: Richard O'Dwyer
Author-email: richard@richard.do
License: Apache 2.0
Platform: UNKNOWN
Classifier: Development Status :: 5 - Production/Stable
Classifier: Intended Audience :: Developers
Classifier: Natural Language :: English
Classifier: License :: OSI Approved :: Apache Software License
Classifier: Operating System :: OS Independent
Classifier: Programming Language :: Python
Classifier: Programming Language :: Python :: 3
Classifier: Programming Language :: Python :: 3.6
Classifier: Programming Language :: Python :: 3.7
Classifier: Programming Language :: Python :: 3.8
Requires-Dist: requirements-parser (<1.0.0,>=0.2.0)
Requires-Dist: pypi-simple (<1.0.0,>=0.4.0)
Requires-Dist: docopt (<1.0.0,>=0.5.0)
Requires-Dist: wheel
